CHANGES.txt
CONTRIBUTORS.txt
README.txt
bootstrap.py
buildout.cfg
setup.py
my315ok/__init__.py
my315ok/__init__.pyc
my315ok.recipe.cpzexp.egg-info/PKG-INFO
my315ok.recipe.cpzexp.egg-info/SOURCES.txt
my315ok.recipe.cpzexp.egg-info/dependency_links.txt
my315ok.recipe.cpzexp.egg-info/entry_points.txt
my315ok.recipe.cpzexp.egg-info/namespace_packages.txt
my315ok.recipe.cpzexp.egg-info/not-zip-safe
my315ok.recipe.cpzexp.egg-info/requires.txt
my315ok.recipe.cpzexp.egg-info/top_level.txt
my315ok/recipe/__init__.py
my315ok/recipe/__init__.pyc
my315ok/recipe/cpzexp/README.txt
my315ok/recipe/cpzexp/__init__.py
my315ok/recipe/cpzexp/tests/__init__.py
my315ok/recipe/cpzexp/tests/test_docs.py