Metadata-Version: 1.0
Name: my315ok.recipe.cpzexp
Version: 1.0
Summary: automatic copy zexps to Plone's import directory
Home-page: http://svn.plone.org/svn/collective/
Author: adam tang
Author-email: yuejun.tang@gmail.com
License: ZPL
Keywords: plone import
Platform: UNKNOWN
Classifier: Framework :: Buildout
Classifier: Intended Audience :: Developers
Classifier: Topic :: Software Development :: Build Tools
Classifier: License :: OSI Approved :: Zope Public License
